MANIFEST.in
README.rst
setup.cfg
setup.py
django_filesnow.egg-info/PKG-INFO
django_filesnow.egg-info/SOURCES.txt
django_filesnow.egg-info/dependency_links.txt
django_filesnow.egg-info/top_level.txt
filesnow/__init__.py
filesnow/admin.py
filesnow/apps.py
filesnow/models.py
filesnow/tests.py
filesnow/urls.py
filesnow/views.py
filesnow/migrations/__init__.py
filesnow/static/filesnow/bootstrap/css/bootstrap-grid.css
filesnow/static/filesnow/bootstrap/css/bootstrap-grid.css.map
filesnow/static/filesnow/bootstrap/css/bootstrap-grid.min.css
filesnow/static/filesnow/bootstrap/css/bootstrap-grid.min.css.map
filesnow/static/filesnow/bootstrap/css/bootstrap-reboot.css
filesnow/static/filesnow/bootstrap/css/bootstrap-reboot.css.map
filesnow/static/filesnow/bootstrap/css/bootstrap-reboot.min.css
filesnow/static/filesnow/bootstrap/css/bootstrap-reboot.min.css.map
filesnow/static/filesnow/bootstrap/css/bootstrap.css
filesnow/static/filesnow/bootstrap/css/bootstrap.css.map
filesnow/static/filesnow/bootstrap/css/bootstrap.min.css
filesnow/static/filesnow/bootstrap/css/bootstrap.min.css.map
filesnow/static/filesnow/bootstrap/js/bootstrap.bundle.js
filesnow/static/filesnow/bootstrap/js/bootstrap.bundle.js.map
filesnow/static/filesnow/bootstrap/js/bootstrap.bundle.min.js
filesnow/static/filesnow/bootstrap/js/bootstrap.bundle.min.js.map
filesnow/static/filesnow/bootstrap/js/bootstrap.js
filesnow/static/filesnow/bootstrap/js/bootstrap.js.map
filesnow/static/filesnow/bootstrap/js/bootstrap.min.js
filesnow/static/filesnow/bootstrap/js/bootstrap.min.js.map
filesnow/static/filesnow/css/indexStyle.css
filesnow/static/filesnow/img/gg.txt
filesnow/static/filesnow/img/label.jpeg
filesnow/static/filesnow/img/price.png
filesnow/static/filesnow/img/qr.png
filesnow/static/filesnow/img/rain.jpeg
filesnow/static/filesnow/img/s3.png
filesnow/static/filesnow/img/sale.png
filesnow/static/filesnow/img/ship.jpeg
filesnow/static/filesnow/img/ship1.jpeg
filesnow/static/filesnow/jquery/jquery-3.4.1.slim.min.js
filesnow/static/filesnow/jquery/popper.min.js
filesnow/static/filesnow/js/ajax.js
filesnow/templates/filesnow/index.html